{
  "Object": "SBQQ__ProductOption__c",
  "References": [
    {
      "Name": "SBQQ__ConfiguredSKU__r",
      "ReferencedObject": "Product2",
      "ReferencedFields": {
        "Gearset_External_Id__c": "b29f2ee0-0e45-47fb-8d1c-76b4fd5a4bb6"
      }
    },
    {
      "Name": "SBQQ__OptionalSKU__r",
      "ReferencedObject": "Product2",
      "ReferencedFields": {
        "Gearset_External_Id__c": "e0bd6f4e-f584-4c61-8e81-14d5e7cf09f2"
      }
    },
    {
      "Name": "SBQQ__Feature__r",
      "ReferencedObject": "SBQQ__ProductFeature__c",
      "ReferencedFields": {
        "Gearset_External_Id__c": "8423e6e5-c19b-4882-aad7-9346509ced5f"
      }
    }
  ],
  "Fields": {
    "SBQQ__AppliedImmediatelyContext__c": "",
    "SBQQ__AppliedImmediately__c": "false",
    "SBQQ__Bundled__c": "false",
    "SBQQ__ComponentCodePosition__c": "",
    "SBQQ__ComponentCode__c": "",
    "SBQQ__ComponentDescriptionPosition__c": "",
    "SBQQ__ComponentDescription__c": "",
    "SBQQ__DefaultPricingTable__c": "",
    "SBQQ__DiscountAmount__c": "",
    "SBQQ__Discount__c": "",
    "SBQQ__DiscountedByPackage__c": "false",
    "SBQQ__ExistingQuantity__c": "",
    "SBQQ__MaxQuantity__c": "",
    "SBQQ__MinQuantity__c": "",
    "SBQQ__Number__c": "30.0",
    "SBQQ__QuantityEditable__c": "false",
    "SBQQ__Quantity__c": "",
    "SBQQ__QuoteLineVisibility__c": "",
    "SBQQ__Required__c": "false",
    "SBQQ__Selected__c": "false",
    "SBQQ__SubscriptionScope__c": "",
    "SBQQ__System__c": "false",
    "SBQQ__Type__c": "Component",
    "SBQQ__UnitPrice__c": "",
    "SBQQ__UpliftedByPackage__c": "false",
    "Gearset_External_Id__c": "c91645f5-5ecc-4b6f-9a94-baf3546c1114",
    "Size__c": "",
    "Accent__c": "",
    "Engraving__c": "",
    "Outlet_Standard__c": "",
    "Material__c": "",
    "Color__c": ""
  }
}